{
  "season": 2026,
  "updated_at": "2026-06-19T19:30:38.723206",
  "players": {
    "Matt Chapman": 7,
    "James Wood": 20,
    "Vlad Guerrero": 4,
    "Corey Seager": 9,
    "Kyle Schwarber": 25,
    "Nolan Gorman": 7,
    "Taylor Ward": 3,
    "Shea Langeliers": 19,
    "Isaac Paredes": 10,
    "Wyatt Langford": 4,
    "Ben Rice": 20,
    "Munetaka Murakami": 20,
    "Austin Riley": 8,
    "Willy Adames": 13,
    "Brice Turang": 11,
    "Kyle Tucker": 6,
    "Juan Soto": 17,
    "Brent Rooker": 10,
    "Giancarlo Stanton": 3,
    "Alec Bohm": 9,
    "Pete Alonso": 16,
    "Salvador Perez": 10,
    "Addison Barger": 0,
    "Kody Clemens": 11,
    "Francisco Lindor": 2,
    "Christian Yelich": 5,
    "Trent Grisham": 8,
    "Riley Greene": 8,
    "Yandy Diaz": 12,
    "Rafael Devers": 10,
    "Jake Burger": 12,
    "Brandon Lowe": 18,
    "Aaron Judge": 17,
    "Francisco Alvarez": 5,
    "Gunnar Henderson": 15,
    "Jose Ramirez": 10,
    "Matt Wallner": 4,
    "Jac Caglianone": 9,
    "Bryce Eldridge": 6,
    "Samuel Basallo": 10,
    "Jazz Chisholm Jr.": 10,
    "Cal Raleigh": 7,
    "Trevor Story": 3,
    "Bryce Harper": 15,
    "Byron Buxton": 23,
    "Manny Machado": 12,
    "Adolis Garcia": 7,
    "Teoscar Hernandez": 7,
    "Oneil Cruz": 14,
    "Freddie Freeman": 12,
    "Will Smith": 6,
    "Ketel Marte": 11,
    "Spencer Torkelson": 12,
    "Bo Bichette": 8,
    "Bobby Witt": 10,
    "Ronald Acuna": 7,
    "Pete Crow-Armstrong": 15,
    "Cody Bellinger": 11,
    "Roman Anthony": 1,
    "Mookie Betts": 7,
    "Carlos Correa": 3,
    "Vinnie Pasquantino": 6,
    "Gleyber Torres": 4,
    "Adley Rutschman": 8,
    "Alex Bregman": 6,
    "Yordan Alvarez": 24,
    "Jorge Polanco": 1,
    "George Springer": 7,
    "Cam Smith": 7,
    "Christian Walker": 18,
    "Jose Altuve": 7,
    "Jo Adell": 10,
    "William Contreras": 6,
    "Elly De La Cruz": 12,
    "Nolan Arenado": 8,
    "Fernando Tatis Jr.": 2,
    "Jackson Merrill": 8,
    "Seiya Suzuki": 10,
    "Shohei Ohtani": 15,
    "Brice Matthews": 6,
    "Yainer Diaz": 2,
    "Matt Olson": 20,
    "Dansby Swanson": 8,
    "Junior Caminero": 15,
    "Jackson Holliday": 4,
    "Mike Trout": 17,
    "Julio Rodriguez": 13,
    "Corbin Carroll": 13,
    "Ian Happ": 16,
    "Jeremy Pena": 4,
    "Zach Neto": 15,
    "Nick Kurtz": 18,
    "Lenyn Sosa": 1,
    "Eugenio Suarez": 7,
    "Hunter Goodman": 21,
    "Daulton Varsho": 5,
    "Brandon Nimmo": 7,
    "Andy Page": 15,
    "Lawrence Butler": 4,
    "Kyle Manzardo": 8
  }
}