{
  "season": 2026,
  "updated_at": "2026-07-12T18:39:57.916916",
  "players": {
    "James Wood": 28,
    "Shea Langeliers": 21,
    "Corey Seager": 10,
    "Kyle Schwarber": 32,
    "Vlad Guerrero": 6,
    "Nolan Gorman": 7,
    "Matt Chapman": 7,
    "Taylor Ward": 6,
    "Wyatt Langford": 9,
    "Munetaka Murakami": 20,
    "Ben Rice": 29,
    "Isaac Paredes": 12,
    "Willy Adames": 15,
    "Brice Turang": 13,
    "Juan Soto": 21,
    "Austin Riley": 9,
    "Alec Bohm": 11,
    "Kyle Tucker": 7,
    "Brent Rooker": 10,
    "Giancarlo Stanton": 3,
    "Pete Alonso": 21,
    "Salvador Perez": 11,
    "Kody Clemens": 16,
    "Francisco Lindor": 4,
    "Riley Greene": 13,
    "Addison Barger": 0,
    "Christian Yelich": 6,
    "Rafael Devers": 19,
    "Yandy Diaz": 13,
    "Francisco Alvarez": 9,
    "Jake Burger": 16,
    "Gunnar Henderson": 17,
    "Brandon Lowe": 21,
    "Jose Ramirez": 10,
    "Trent Grisham": 10,
    "Aaron Judge": 17,
    "Matt Wallner": 4,
    "Jac Caglianone": 15,
    "Samuel Basallo": 15,
    "Cal Raleigh": 9,
    "Bryce Eldridge": 8,
    "Jazz Chisholm Jr.": 13,
    "Bryce Harper": 20,
    "Trevor Story": 3,
    "Manny Machado": 19,
    "Byron Buxton": 25,
    "Teoscar Hernandez": 8,
    "Adolis Garcia": 7,
    "Oneil Cruz": 14,
    "Freddie Freeman": 15,
    "Will Smith": 6,
    "Spencer Torkelson": 16,
    "Ketel Marte": 17,
    "Bobby Witt": 13,
    "Bo Bichette": 10,
    "Roman Anthony": 1,
    "Pete Crow-Armstrong": 21,
    "Cody Bellinger": 11,
    "Ronald Acuna": 7,
    "Carlos Correa": 3,
    "Adley Rutschman": 8,
    "Vinnie Pasquantino": 6,
    "Gleyber Torres": 4,
    "Alex Bregman": 8,
    "Mookie Betts": 11,
    "Jo Adell": 13,
    "Yordan Alvarez": 31,
    "Jorge Polanco": 1,
    "Cam Smith": 11,
    "George Springer": 9,
    "William Contreras": 9,
    "Christian Walker": 20,
    "Elly De La Cruz": 15,
    "Jose Altuve": 10,
    "Fernando Tatis Jr.": 5,
    "Nolan Arenado": 12,
    "Jackson Merrill": 10,
    "Seiya Suzuki": 15,
    "Shohei Ohtani": 21,
    "Brice Matthews": 7,
    "Matt Olson": 25,
    "Dansby Swanson": 16,
    "Jackson Holliday": 5,
    "Yainer Diaz": 6,
    "Junior Caminero": 28,
    "Corbin Carroll": 13,
    "Julio Rodriguez": 14,
    "Mike Trout": 18,
    "Ian Happ": 17,
    "Jeremy Pena": 6,
    "Hunter Goodman": 27,
    "Nick Kurtz": 20,
    "Zach Neto": 19,
    "Lenyn Sosa": 1,
    "Eugenio Suarez": 10,
    "Daulton Varsho": 7,
    "Andy Page": 17,
    "Brandon Nimmo": 9,
    "Lawrence Butler": 5,
    "Kyle Manzardo": 10
  }
}