{
  "season": 2026,
  "updated_at": "2026-06-04T19:30:35.473052",
  "players": {
    "Matt Chapman": 2,
    "Nolan Gorman": 7,
    "Kyle Schwarber": 23,
    "Shea Langeliers": 14,
    "Corey Seager": 7,
    "Taylor Ward": 2,
    "Vlad Guerrero": 3,
    "James Wood": 16,
    "Wyatt Langford": 1,
    "Ben Rice": 17,
    "Munetaka Murakami": 20,
    "Isaac Paredes": 7,
    "Brice Turang": 7,
    "Willy Adames": 9,
    "Juan Soto": 13,
    "Austin Riley": 8,
    "Kyle Tucker": 5,
    "Brent Rooker": 8,
    "Alec Bohm": 6,
    "Salvador Perez": 9,
    "Pete Alonso": 12,
    "Giancarlo Stanton": 3,
    "Kody Clemens": 6,
    "Francisco Lindor": 2,
    "Addison Barger": 0,
    "Riley Greene": 6,
    "Trent Grisham": 7,
    "Christian Yelich": 4,
    "Rafael Devers": 7,
    "Jake Burger": 10,
    "Yandy Diaz": 11,
    "Francisco Alvarez": 4,
    "Gunnar Henderson": 13,
    "Brandon Lowe": 15,
    "Jose Ramirez": 9,
    "Aaron Judge": 17,
    "Matt Wallner": 4,
    "Jac Caglianone": 6,
    "Samuel Basallo": 9,
    "Bryce Eldridge": 2,
    "Cal Raleigh": 7,
    "Bryce Harper": 14,
    "Manny Machado": 11,
    "Jazz Chisholm Jr.": 7,
    "Trevor Story": 3,
    "Adolis Garcia": 5,
    "Byron Buxton": 17,
    "Oneil Cruz": 14,
    "Teoscar Hernandez": 7,
    "Freddie Freeman": 9,
    "Spencer Torkelson": 8,
    "Will Smith": 6,
    "Ketel Marte": 10,
    "Bobby Witt": 9,
    "Bo Bichette": 5,
    "Ronald Acuna": 7,
    "Pete Crow-Armstrong": 8,
    "Roman Anthony": 1,
    "Cody Bellinger": 8,
    "Carlos Correa": 3,
    "Adley Rutschman": 7,
    "Gleyber Torres": 3,
    "Vinnie Pasquantino": 6,
    "Alex Bregman": 5,
    "Mookie Betts": 6,
    "Yordan Alvarez": 21,
    "Jo Adell": 9,
    "Jorge Polanco": 1,
    "George Springer": 5,
    "William Contreras": 4,
    "Cam Smith": 6,
    "Jose Altuve": 4,
    "Christian Walker": 16,
    "Elly De La Cruz": 12,
    "Fernando Tatis Jr.": 1,
    "Nolan Arenado": 8,
    "Jackson Merrill": 5,
    "Seiya Suzuki": 8,
    "Shohei Ohtani": 10,
    "Yainer Diaz": 2,
    "Brice Matthews": 4,
    "Jackson Holliday": 2,
    "Matt Olson": 17,
    "Dansby Swanson": 7,
    "Junior Caminero": 14,
    "Corbin Carroll": 8,
    "Julio Rodriguez": 13,
    "Mike Trout": 14,
    "Ian Happ": 13,
    "Hunter Goodman": 15,
    "Jeremy Pena": 3,
    "Nick Kurtz": 11,
    "Lenyn Sosa": 1,
    "Zach Neto": 10,
    "Daulton Varsho": 5,
    "Andy Page": 13,
    "Eugenio Suarez": 4,
    "Brandon Nimmo": 7,
    "Lawrence Butler": 3,
    "Kyle Manzardo": 7
  }
}