{
  "season": 2026,
  "updated_at": "2026-04-14T00:45:32.197264",
  "players": {
    "James Wood": 5,
    "Kyle Schwarber": 6,
    "Matt Chapman": 1,
    "Vlad Guerrero": 1,
    "Taylor Ward": 0,
    "Shea Langeliers": 5,
    "Nolan Gorman": 2,
    "Corey Seager": 4,
    "Isaac Paredes": 0,
    "Ben Rice": 4,
    "Wyatt Langford": 1,
    "Austin Riley": 0,
    "Brice Turang": 3,
    "Willy Adames": 2,
    "Munetaka Murakami": 4,
    "Juan Soto": 1,
    "Kyle Tucker": 1,
    "Giancarlo Stanton": 1,
    "Brent Rooker": 2,
    "Alec Bohm": 1,
    "Kody Clemens": 2,
    "Salvador Perez": 2,
    "Pete Alonso": 1,
    "Francisco Lindor": 0,
    "Riley Greene": 1,
    "Addison Barger": 0,
    "Trent Grisham": 0,
    "Christian Yelich": 1,
    "Rafael Devers": 2,
    "Yandy Diaz": 3,
    "Jake Burger": 2,
    "Francisco Alvarez": 4,
    "Brandon Lowe": 5,
    "Bryce Eldridge": 0,
    "Gunnar Henderson": 6,
    "Aaron Judge": 5,
    "Matt Wallner": 3,
    "Jose Ramirez": 2,
    "Samuel Basallo": 2,
    "Jac Caglianone": 0,
    "Cal Raleigh": 2,
    "Bryce Harper": 3,
    "Jazz Chisholm Jr.": 0,
    "Trevor Story": 1,
    "Byron Buxton": 0,
    "Manny Machado": 2,
    "Adolis Garcia": 2,
    "Teoscar Hernandez": 3,
    "Oneil Cruz": 5,
    "Freddie Freeman": 3,
    "Will Smith": 2,
    "Ketel Marte": 4,
    "Spencer Torkelson": 0,
    "Bo Bichette": 1,
    "Bobby Witt": 0,
    "Ronald Acuna": 1,
    "Pete Crow-Armstrong": 1,
    "Roman Anthony": 1,
    "Cody Bellinger": 1,
    "Vinnie Pasquantino": 0,
    "Carlos Correa": 1,
    "Gleyber Torres": 1,
    "Adley Rutschman": 0,
    "Alex Bregman": 2,
    "Mookie Betts": 2,
    "Yordan Alvarez": 6,
    "Jo Adell": 1,
    "Cam Smith": 3,
    "Jorge Polanco": 1,
    "Jose Altuve": 2,
    "Christian Walker": 3,
    "William Contreras": 2,
    "Nolan Arenado": 2,
    "Elly De La Cruz": 5,
    "George Springer": 2,
    "Fernando Tatis Jr.": 0,
    "Seiya Suzuki": 0,
    "Jackson Merrill": 3,
    "Brice Matthews": 1,
    "Shohei Ohtani": 5,
    "Matt Olson": 4,
    "Yainer Diaz": 1,
    "Jackson Holliday": 0,
    "Dansby Swanson": 3,
    "Corbin Carroll": 2,
    "Junior Caminero": 2,
    "Julio Rodriguez": 1,
    "Ian Happ": 4,
    "Mike Trout": 2,
    "Jeremy Pena": 0,
    "Hunter Goodman": 2,
    "Nick Kurtz": 1,
    "Lenyn Sosa": 0,
    "Andy Page": 4,
    "Zach Neto": 5,
    "Eugenio Suarez": 2,
    "Brandon Nimmo": 3,
    "Daulton Varsho": 2,
    "Kyle Manzardo": 1,
    "Lawrence Butler": 1
  }
}