{
  "season": 2026,
  "updated_at": "2026-05-06T17:00:36.264109",
  "players": {
    "Nolan Gorman": 5,
    "Matt Chapman": 1,
    "Vlad Guerrero": 2,
    "Taylor Ward": 1,
    "Corey Seager": 6,
    "James Wood": 10,
    "Kyle Schwarber": 11,
    "Shea Langeliers": 10,
    "Isaac Paredes": 3,
    "Wyatt Langford": 1,
    "Brice Turang": 5,
    "Ben Rice": 12,
    "Munetaka Murakami": 14,
    "Willy Adames": 3,
    "Austin Riley": 5,
    "Juan Soto": 3,
    "Kyle Tucker": 4,
    "Brent Rooker": 3,
    "Salvador Perez": 5,
    "Giancarlo Stanton": 3,
    "Alec Bohm": 1,
    "Pete Alonso": 6,
    "Kody Clemens": 3,
    "Francisco Lindor": 2,
    "Addison Barger": 0,
    "Riley Greene": 4,
    "Trent Grisham": 5,
    "Christian Yelich": 1,
    "Yandy Diaz": 5,
    "Rafael Devers": 2,
    "Francisco Alvarez": 4,
    "Jake Burger": 6,
    "Brandon Lowe": 8,
    "Gunnar Henderson": 9,
    "Jose Ramirez": 6,
    "Matt Wallner": 3,
    "Jac Caglianone": 4,
    "Aaron Judge": 14,
    "Samuel Basallo": 5,
    "Bryce Eldridge": 0,
    "Cal Raleigh": 7,
    "Jazz Chisholm Jr.": 4,
    "Bryce Harper": 9,
    "Byron Buxton": 11,
    "Manny Machado": 5,
    "Trevor Story": 2,
    "Teoscar Hernandez": 4,
    "Adolis Garcia": 3,
    "Freddie Freeman": 3,
    "Oneil Cruz": 9,
    "Spencer Torkelson": 6,
    "Will Smith": 3,
    "Bo Bichette": 2,
    "Bobby Witt": 3,
    "Ketel Marte": 5,
    "Ronald Acuna": 2,
    "Roman Anthony": 1,
    "Cody Bellinger": 5,
    "Pete Crow-Armstrong": 3,
    "Carlos Correa": 3,
    "Gleyber Torres": 2,
    "Adley Rutschman": 4,
    "Mookie Betts": 2,
    "Vinnie Pasquantino": 4,
    "Alex Bregman": 3,
    "George Springer": 2,
    "Yordan Alvarez": 12,
    "Jo Adell": 4,
    "William Contreras": 3,
    "Cam Smith": 4,
    "Jorge Polanco": 1,
    "Christian Walker": 9,
    "Jose Altuve": 3,
    "Elly De La Cruz": 10,
    "Fernando Tatis Jr.": 0,
    "Nolan Arenado": 5,
    "Shohei Ohtani": 6,
    "Seiya Suzuki": 6,
    "Jackson Merrill": 4,
    "Brice Matthews": 3,
    "Jackson Holliday": 0,
    "Yainer Diaz": 2,
    "Matt Olson": 13,
    "Dansby Swanson": 6,
    "Junior Caminero": 9,
    "Corbin Carroll": 4,
    "Julio Rodriguez": 4,
    "Mike Trout": 11,
    "Ian Happ": 8,
    "Jeremy Pena": 0,
    "Hunter Goodman": 9,
    "Lenyn Sosa": 1,
    "Nick Kurtz": 5,
    "Eugenio Suarez": 3,
    "Zach Neto": 6,
    "Daulton Varsho": 4,
    "Andy Page": 5,
    "Brandon Nimmo": 4,
    "Lawrence Butler": 3,
    "Kyle Manzardo": 2
  }
}