{
  "season": 2026,
  "updated_at": "2026-04-28T21:00:36.735072",
  "players": {
    "Shea Langeliers": 8,
    "Kyle Schwarber": 9,
    "Matt Chapman": 1,
    "James Wood": 10,
    "Vlad Guerrero": 2,
    "Corey Seager": 6,
    "Nolan Gorman": 3,
    "Taylor Ward": 1,
    "Wyatt Langford": 1,
    "Munetaka Murakami": 12,
    "Isaac Paredes": 3,
    "Ben Rice": 10,
    "Willy Adames": 3,
    "Brice Turang": 4,
    "Austin Riley": 3,
    "Juan Soto": 1,
    "Kyle Tucker": 3,
    "Alec Bohm": 1,
    "Kody Clemens": 3,
    "Brent Rooker": 2,
    "Pete Alonso": 3,
    "Giancarlo Stanton": 3,
    "Salvador Perez": 4,
    "Francisco Lindor": 2,
    "Trent Grisham": 4,
    "Addison Barger": 0,
    "Christian Yelich": 1,
    "Riley Greene": 3,
    "Rafael Devers": 2,
    "Francisco Alvarez": 4,
    "Yandy Diaz": 4,
    "Jake Burger": 5,
    "Brandon Lowe": 7,
    "Gunnar Henderson": 9,
    "Aaron Judge": 11,
    "Jose Ramirez": 6,
    "Matt Wallner": 3,
    "Bryce Eldridge": 0,
    "Samuel Basallo": 5,
    "Jac Caglianone": 2,
    "Cal Raleigh": 7,
    "Bryce Harper": 6,
    "Jazz Chisholm Jr.": 3,
    "Manny Machado": 4,
    "Trevor Story": 2,
    "Byron Buxton": 6,
    "Adolis Garcia": 3,
    "Teoscar Hernandez": 4,
    "Oneil Cruz": 8,
    "Freddie Freeman": 3,
    "Will Smith": 3,
    "Bo Bichette": 1,
    "Ketel Marte": 4,
    "Spencer Torkelson": 5,
    "Ronald Acuna": 2,
    "Bobby Witt": 1,
    "Roman Anthony": 1,
    "Pete Crow-Armstrong": 1,
    "Cody Bellinger": 3,
    "Vinnie Pasquantino": 3,
    "Carlos Correa": 2,
    "Gleyber Torres": 2,
    "Adley Rutschman": 3,
    "Alex Bregman": 3,
    "Mookie Betts": 2,
    "Yordan Alvarez": 11,
    "Jo Adell": 4,
    "Jorge Polanco": 1,
    "Cam Smith": 3,
    "Jose Altuve": 3,
    "William Contreras": 2,
    "George Springer": 2,
    "Elly De La Cruz": 9,
    "Christian Walker": 7,
    "Nolan Arenado": 4,
    "Fernando Tatis Jr.": 0,
    "Jackson Merrill": 3,
    "Seiya Suzuki": 5,
    "Brice Matthews": 1,
    "Yainer Diaz": 2,
    "Shohei Ohtani": 6,
    "Jackson Holliday": 0,
    "Matt Olson": 8,
    "Dansby Swanson": 6,
    "Junior Caminero": 8,
    "Mike Trout": 9,
    "Julio Rodriguez": 2,
    "Corbin Carroll": 3,
    "Hunter Goodman": 7,
    "Jeremy Pena": 0,
    "Nick Kurtz": 5,
    "Ian Happ": 7,
    "Eugenio Suarez": 3,
    "Daulton Varsho": 3,
    "Andy Page": 5,
    "Zach Neto": 5,
    "Brandon Nimmo": 4,
    "Lenyn Sosa": 0,
    "Lawrence Butler": 2,
    "Kyle Manzardo": 1
  }
}